{"years": [2026, 2027, 2028], "proj": {"pid": "12455", "name": "Brashard Smith", "pos": "RB", "team": "Unsolicited Nix pics", "age": 22, "age_src": "matched", "pick": 228, "exp": 1, "elite": 0, "war25": -0.795, "career": [[2025, -0.795]], "availAdj": 0.0, "level": -0.85, "proj": [-0.651, -0.628, -0.745], "nat_low": [-1.103, -1.081, -1.173], "nat_high": [-0.18, -0.158, -0.303], "expected": [-0.53, -0.511, -0.608], "adj_low": [-0.898, -0.88, -0.957], "adj_high": [-0.147, -0.128, -0.247], "composite": [-1.084, -0.899, -0.853], "comp_low": [-1.537, -1.352, -1.281], "comp_high": [-0.614, -0.429, -0.411], "ppg": 1.94, "bye": 5, "proj_ext": -1.192, "total": -2.024, "total_exp": -1.649, "total_comp": -2.836, "posFin": [101, 95, 101]}, "sproj": {"pos": "RB", "pts13": 15.22, "ppg": 1.17, "raw_pts": 19.9}}