{"years": [2026, 2027, 2028], "proj": {"pid": "12516", "name": "Kalel Mullings", "pos": "RB", "team": "These Bitches Love 'Doza", "age": 22, "age_src": "matched", "pick": 188, "exp": 1, "elite": 0, "war25": -0.427, "career": [[2025, -0.427]], "availAdj": 0.0, "level": -0.952, "proj": [-0.734, -0.688, -0.799], "nat_low": [-1.186, -1.14, -1.227], "nat_high": [-0.263, -0.217, -0.357], "expected": [-0.597, -0.56, -0.652], "adj_low": [-0.966, -0.928, -1.001], "adj_high": [-0.214, -0.177, -0.291], "composite": [-1.195, -0.999, -0.901], "comp_low": [-1.648, -1.452, -1.329], "comp_high": [-0.725, -0.528, -0.459], "ppg": 1.15, "bye": 9, "proj_ext": -1.31, "total": -2.221, "total_exp": -1.809, "total_comp": -3.095, "posFin": [103, 103, 106]}, "sproj": {"pos": "RB", "pts13": 4.28, "ppg": 0.33, "raw_pts": 5.6}}