{"years": [2026, 2027, 2028], "proj": {"pid": "12531", "name": "Trevor Etienne", "pos": "RB", "team": "Bijan al-Gaib", "age": 21, "age_src": "matched", "pick": 114, "exp": 1, "elite": 0, "war25": -1.012, "career": [[2025, -1.012]], "availAdj": 0.0, "level": -0.759, "proj": [-0.577, -0.547, -0.511], "nat_low": [-1.029, -1.0, -0.964], "nat_high": [-0.106, -0.077, -0.041], "expected": [-0.47, -0.445, -0.416], "adj_low": [-0.838, -0.814, -0.784], "adj_high": [-0.087, -0.062, -0.033], "composite": [-0.995, -0.824, -0.629], "comp_low": [-1.448, -1.277, -1.082], "comp_high": [-0.524, -0.353, -0.159], "ppg": 2.58, "bye": 5, "proj_ext": -1.1, "total": -1.635, "total_exp": -1.331, "total_comp": -2.448, "posFin": [85, 82, 73]}, "sproj": {"pos": "RB", "pts13": 23.78, "ppg": 1.83, "raw_pts": 31.1}}