{"years": [2026, 2027, 2028], "proj": {"pid": "1339", "name": "Zach Ertz", "pos": "TE", "team": "Captain Jah\u2019Merica", "age": 34, "age_src": "matched", "pick": 35, "exp": 13, "elite": 1, "war25": 0.311, "career": [[2013, -0.372], [2014, -0.05], [2015, 0.093], [2016, 0.512], [2017, 1.021], [2018, 1.525], [2019, 1.118], [2020, -0.142], [2021, 0.25], [2022, 0.471], [2023, -0.003], [2024, 0.347], [2025, 0.311]], "availAdj": -0.055, "level": 0.302, "proj": [0.036, -0.001, -0.047], "nat_low": [-0.28, -0.317, -0.363], "nat_high": [0.351, 0.315, 0.268], "expected": [0.027, -0.0, -0.035], "adj_low": [-0.211, -0.239, -0.274], "adj_high": [0.265, 0.237, 0.202], "composite": [-0.788, -0.516, -0.253], "comp_low": [-1.104, -0.832, -0.569], "comp_high": [-0.473, -0.201, 0.062], "ppg": 4.09, "bye": null, "proj_ext": -0.994, "total": -0.012, "total_exp": -0.008, "total_comp": -1.557, "posFin": [47, 36, 23]}, "sproj": {"pos": "TE", "pts13": 34.18, "ppg": 2.63, "raw_pts": 44.7}}