{"years": [2026, 2027, 2028], "proj": {"pid": "5086", "name": "Marquez Valdes-Scantling", "pos": "WR", "team": "Captain Jah\u2019Merica", "age": 30, "age_src": "matched", "pick": 174, "exp": 8, "elite": 0, "war25": -0.493, "career": [[2018, -0.439], [2019, -0.509], [2020, -0.126], [2021, -0.16], [2022, -0.296], [2023, -0.35], [2024, 0.068], [2025, -0.493]], "availAdj": -0.103, "level": -1.017, "proj": [-1.133, -1.17, -1.175], "nat_low": [-1.555, -1.592, -1.597], "nat_high": [-0.779, -0.816, -0.821], "expected": [-0.765, -0.79, -0.794], "adj_low": [-1.05, -1.075, -1.079], "adj_high": [-0.526, -0.551, -0.554], "composite": [-1.154, -1.183, -1.18], "comp_low": [-1.576, -1.605, -1.602], "comp_high": [-0.8, -0.829, -0.826], "ppg": 1.62, "bye": 14, "proj_ext": -1.159, "total": -3.478, "total_exp": -2.349, "total_comp": -3.517, "posFin": [150, 156, 156]}, "sproj": {"pos": "WR", "pts13": 20.57, "ppg": 1.58, "raw_pts": 26.9}}