{"years": [2026, 2027, 2028], "proj": {"pid": "6803", "name": "Brandon Aiyuk", "pos": "WR", "team": "Unsolicited Nix pics", "age": 27, "age_src": "matched", "pick": 25, "exp": 6, "elite": 0, "war25": 0.0, "career": [[2020, 0.593], [2021, -0.037], [2022, 0.695], [2023, 0.942], [2024, -0.009]], "availAdj": -0.017, "level": 0.239, "proj": [0.061, -0.019, -0.237], "nat_low": [0.0, 0.0, 0.0], "nat_high": [0.44, 0.36, 0.117], "expected": [0.052, -0.016, -0.181], "adj_low": [0.0, 0.0, 0.0], "adj_high": [0.372, 0.304, 0.089], "composite": [-0.245, 0.04, 0.06], "comp_low": [0.0, 0.0, 0.0], "comp_high": [0.134, 0.419, 0.414], "proj_ext": -0.321, "total": -0.195, "total_exp": -0.145, "total_comp": -0.145}, "sproj": {"pos": "WR", "pts13": 98.49, "ppg": 7.58, "raw_pts": 128.8}}