{"years": [2026, 2027, 2028], "proj": {"pid": "8210", "name": "Chig Okonkwo", "pos": "TE", "team": "Homie G Slicer\u2019s Team", "age": 25, "age_src": "matched", "pick": 143, "exp": 4, "elite": 0, "war25": -0.083, "career": [[2022, -0.431], [2023, -0.157], [2024, -0.372], [2025, -0.083]], "availAdj": 0.059, "level": -0.206, "proj": [-0.193, -0.348, -0.388], "nat_low": [0.0, 0.0, 0.0], "nat_high": [0.117, -0.032, -0.072], "expected": [-0.166, -0.302, -0.337], "adj_low": [0.0, 0.0, 0.0], "adj_high": [0.1, -0.028, -0.063], "composite": [0.026, -0.133, -0.294], "comp_low": [0.0, 0.0, 0.0], "comp_high": [0.336, 0.182, 0.021], "ppg": 9.88, "proj_ext": 0.081, "total": -0.929, "total_exp": -0.805, "total_comp": -0.401}, "sproj": {"pos": "TE", "pts13": 133.52, "ppg": 10.27, "raw_pts": 174.6}}