{"years": [2026, 2027, 2028], "proj": {"pid": "9229", "name": "Anthony Richardson", "pos": "QB", "team": "Baby Billys Bible Bonkers", "age": 23, "age_src": "matched", "pick": 4, "exp": 3, "elite": 0, "war25": -0.212, "career": [[2023, 0.334], [2024, 0.274], [2025, -0.212]], "availAdj": -0.333, "level": 0.513, "proj": [0.678, 0.7, 0.495], "nat_low": [0.248, 0.27, 0.083], "nat_high": [1.127, 1.149, 0.952], "expected": [0.323, 0.333, 0.19], "adj_low": [0.118, 0.128, 0.032], "adj_high": [0.536, 0.546, 0.366], "composite": [-0.72, -0.174, 0.145], "comp_low": [-1.151, -0.605, -0.267], "comp_high": [-0.271, 0.275, 0.602], "ppg": 4.56, "bye": 13, "proj_ext": -1.07, "total": 1.873, "total_exp": 0.846, "total_comp": -0.749, "posFin": [40, 40, 39]}, "sproj": {"pos": "QB", "pts13": 26.41, "ppg": 2.03, "raw_pts": 34.5}}